pyiets/__init__.py
pyiets/artaios.py
pyiets/preprocess.py
pyiets/read.py
pyiets/restart.py
pyiets/sp.py
pyiets/troisi.py
pyiets/version.py
pyiets/atoms/__init__.py
pyiets/atoms/molecule.py
pyiets/atoms/vibration.py
pyiets/io/__init__.py
pyiets/io/checkinput.py
pyiets/io/gaussianio.py
pyiets/io/snfio.py
pyiets/io/turbomoleio.py
pyiets/runcalcs/__init__.py
pyiets/runcalcs/artaios.py
pyiets/runcalcs/calcmanager.py
pyiets/runcalcs/g092unform.py
pyiets/runcalcs/gaussian.py
pyiets/runcalcs/tm2unformcl.py
pyiets/runcalcs/tm2unformsoc.py
pyiets/runcalcs/turbomole.py
pyiets-0.1.17.data/data/input_defaults.json
pyiets-0.1.17.data/data/isotope_masses.json
pyiets-0.1.17.data/scripts/pyiets
pyiets-0.1.17.data/scripts/pyiets-clean
pyiets-0.1.17.data/scripts/pyiets-compplot
pyiets-0.1.17.data/scripts/pyiets-gaussian-broadening
pyiets-0.1.17.data/scripts/pyiets-plot
pyiets-0.1.17.data/scripts/pyiets-plot-spindiff
pyiets-0.1.17.data/scripts/pyiets-plot-spindiff-gaussian
pyiets-0.1.17.dist-info/LICENSE
pyiets-0.1.17.dist-info/METADATA
pyiets-0.1.17.dist-info/WHEEL
pyiets-0.1.17.dist-info/top_level.txt
pyiets-0.1.17.dist-info/RECORD
