Metadata-Version: 2.1
Name: pyiets
Version: 0.1.17
Summary: A tool for calculating inelastic tunneling spectra
Home-page: UNKNOWN
Author: Benjamin Bolbrinker, Michael Deffner, Martin Zoellner, Carmen Herrmann
Author-email: benjamin.bolbrinker@chemie.uni.hamburg.de
License: UNKNOWN
Platform: UNKNOWN
Classifier: Programming Language :: Python :: 3
Classifier: License :: OSI Approved :: GNU General Public License v3 (GPLv3)
Classifier: Operating System :: POSIX :: Linux
Requires-Dist: numpy (==1.15.2)
Requires-Dist: cclib (==1.6.1)
Requires-Dist: ase (==3.16.2)
Requires-Dist: sphinx (==1.8.4)
Requires-Dist: sphinxcontrib-bibtex (==0.4.2)
Requires-Dist: numpydoc (==0.8.0)
Requires-Dist: sphinx-rtd-theme (==0.4.3)
Requires-Dist: mendeleev (==0.4.4)
Requires-Dist: matplotlib (==3.0.0)
